MANIFEST.in
README.rst
setup.py
tests/integration/__init__.py
tests/integration/example_test.py
tests/integration/finder_test.py
tests/unit/__init__.py
tests/unit/example_test.py
tests/unit/podcast_test.py
tests/unit/controlers/__init__.py
tests/unit/controlers/youtube/__init__.py
tests/unit/controlers/youtube/movie_test.py
ytrss/__init__.py
ytrss/__main__.py
ytrss/client.py
ytrss.egg-info/PKG-INFO
ytrss.egg-info/SOURCES.txt
ytrss.egg-info/dependency_links.txt
ytrss.egg-info/entry_points.txt
ytrss.egg-info/requires.txt
ytrss.egg-info/top_level.txt
ytrss/commands/__init__.py
ytrss/commands/configuration.py
ytrss/commands/download.py
ytrss/commands/generate.py
ytrss/commands/run.py
ytrss/commands/url.py
ytrss/commands/version.py
ytrss/configuration/__init__.py
ytrss/configuration/configuration.py
ytrss/configuration/factory.py
ytrss/configuration/entity/__init__.py
ytrss/configuration/entity/configuration_data.py
ytrss/configuration/entity/destination_info.py
ytrss/configuration/entity/source.py
ytrss/configuration/readers/__init__.py
ytrss/configuration/readers/base.py
ytrss/configuration/readers/default_configuration.py
ytrss/configuration/readers/json_configuration.py
ytrss/configuration/readers/yaml_configuration.py
ytrss/core/__init__.py
ytrss/core/algoritms/__init__.py
ytrss/core/algoritms/download.py
ytrss/core/algoritms/finder.py
ytrss/core/entity/__init__.py
ytrss/core/entity/destination.py
ytrss/core/entity/downloaded_movie.py
ytrss/core/entity/downloader.py
ytrss/core/entity/movie.py
ytrss/core/entity/source_downloader.py
ytrss/core/factory/__init__.py
ytrss/core/factory/destination.py
ytrss/core/factory/downloader.py
ytrss/core/factory/movie.py
ytrss/core/factory/source_downloader.py
ytrss/core/helpers/__init__.py
ytrss/core/helpers/files.py
ytrss/core/helpers/logging.py
ytrss/core/helpers/string_utils.py
ytrss/core/helpers/typing.py
ytrss/core/managers/__init__.py
ytrss/core/managers/destination_manager.py
ytrss/core/managers/manager_service.py
ytrss/core/managers/sources_manager.py
ytrss/database/__init__.py
ytrss/database/database.py
ytrss/database/sqlite/__init__.py
ytrss/database/sqlite/sqlite_database.py
