Metadata-Version: 2.1
Name: ytrss
Version: 0.3.2
Summary: Tools for downloading mp3 from YouTube subscription and playlists.
Home-page: https://github.com/rafyco/ytrss.git
Author: Rafal Kobel
Author-email: rafalkobel@rafyco.pl
License: GNU
Project-URL: Source, https://github.com/rafyco/ytrss
Project-URL: Tracker, https://github.com/rafyco/ytrss/issues
Project-URL: Changelog, https://github.com/rafyco/ytrss/blob/master/dosc/changelog.rst
Project-URL: Documentation, https://ytrss.readthedocs.io
Keywords: youtube,console,download,rss,mp3,service
Platform: Any
Classifier: Environment :: Console
Classifier: Development Status :: 3 - Alpha
Classifier: Topic :: Multimedia :: Sound/Audio
Classifier: Programming Language :: Python :: 3
Classifier: Programming Language :: Python :: 3.6
Classifier: License :: OSI Approved :: GNU General Public License v3 (GPLv3)
Requires-Python: >=3.6
Provides-Extra: documentation
Provides-Extra: style
Provides-Extra: unittests
Provides-Extra: typing
Provides-Extra: optional
